simpleobsws.py
simpleobsws-1.4.3.dist-info/licenses/LICENSE
simpleobsws-1.4.3.dist-info/METADATA
simpleobsws-1.4.3.dist-info/WHEEL
simpleobsws-1.4.3.dist-info/top_level.txt
simpleobsws-1.4.3.dist-info/RECORD
