Metadata-Version: 2.4
Name: simpleobsws
Version: 1.4.3
Summary: A simple obs-websocket library in async Python for people who just want JSON output.
Home-page: https://github.com/IRLToolkit/simpleobsws
Author: tt2468
Author-email: tt2468@gmail.com
Classifier: Programming Language :: Python :: 3
Classifier: License :: OSI Approved :: MIT License
Classifier: Operating System :: OS Independent
Classifier: Intended Audience :: Developers
Classifier: Environment :: Plugins
Requires-Python: >=3.9
License-File: LICENSE
Requires-Dist: websockets>=14.0
Requires-Dist: msgpack
Dynamic: author
Dynamic: author-email
Dynamic: classifier
Dynamic: description
Dynamic: description-content-type
Dynamic: home-page
Dynamic: license-file
Dynamic: requires-dist
Dynamic: requires-python
Dynamic: summary
